web3_proxy/__init__.py
web3_proxy/providers/__init__.py
web3_proxy/providers/_async/__init__.py
web3_proxy/providers/_async/http.py
web3_proxy/providers/_sync/__init__.py
web3_proxy/providers/base.py
web3_proxy/utils/__init__.py
web3_proxy/utils/logger.py
web3_proxy/utils/meta.py
web3_proxy/utils/request.py
web3_proxy-0.0.1.dist-info/LICENSE
web3_proxy-0.0.1.dist-info/METADATA
web3_proxy-0.0.1.dist-info/WHEEL
web3_proxy-0.0.1.dist-info/RECORD
