Metadata-Version: 2.1
Name: web3-proxy
Version: 0.0.1
Summary: SOCKS5 & more proxy providers for web3py.
License: Apache 2.0
Author: BlackCatDevel0per
Author-email: bcdev@mail.ru
Requires-Python: >=3.8.1,<4.0
Classifier: Framework :: AsyncIO
Classifier: Intended Audience :: Developers
Classifier: Intended Audience :: System Administrators
Classifier: License :: OSI Approved :: Apache Software License
Classifier: License :: Other/Proprietary License
Classifier: Operating System :: OS Independent
Classifier: Programming Language :: Python :: 3
Classifier: Programming Language :: Python :: 3.9
Classifier: Programming Language :: Python :: 3.10
Classifier: Programming Language :: Python :: 3.11
Classifier: Programming Language :: Python :: 3.12
Classifier: Programming Language :: Python :: 3.8
Classifier: Programming Language :: Python :: Implementation :: PyPy
Classifier: Topic :: Software Development :: Libraries :: Python Modules
Classifier: Typing :: Typed
Requires-Dist: aiohttp (>=3.10.0,<4.0.0)
Requires-Dist: aiohttp-socks (>=0.9.0,<0.10.0)
Requires-Dist: pysocks (>=1.7.1,<2.0.0)
Requires-Dist: web3 (>=6.20.1,<7.0.0)
Requires-Dist: websockets (>=12.0,<13.0)
Project-URL: Documentation, https://github.com/BlackCatDevel0per/web3-proxy
Project-URL: Homepage, https://github.com/BlackCatDevel0per/web3-proxy
Project-URL: Repository, https://github.com/BlackCatDevel0per/web3-proxy
